vacuumworld/__init__.py
vacuumworld/autocomplete.py
vacuumworld/observer.py
vacuumworld/saveload.py
vacuumworld/slider.py
vacuumworld/vw.py
vacuumworld/vwaction.py
vacuumworld/vwactuator.py
vacuumworld/vwagent.py
vacuumworld/vwenvironment.py
vacuumworld/vwperception.py
vacuumworld/vwsensor.py
vacuumworld/vwtooltips.py
vacuumworld/vwuser.py
vacuumworld/vwutils.py
vacuumworld/vwv.py
vacuumworld/res/button.png
vacuumworld/res/difficulty.png
vacuumworld/res/fast.png
vacuumworld/res/guide.png
vacuumworld/res/load.png
vacuumworld/res/pause.png
vacuumworld/res/play.png
vacuumworld/res/reset.png
vacuumworld/res/save.png
vacuumworld/res/start_menu.png
vacuumworld/res/stop.png
vacuumworld/res/locations/agent/green.png
vacuumworld/res/locations/agent/orange.png
vacuumworld/res/locations/agent/user.png
vacuumworld/res/locations/agent/white.png
vacuumworld/res/locations/dirt/green_dirt.png
vacuumworld/res/locations/dirt/orange_dirt.png
vacuumworld/test/__init__.py
vacuumworld/test/test.py
vacuumworld/test/test2.py
vacuumworld/test/test3.py
vacuumworld/test/test_vwc.py
vacuumworld/test/vw_test.py
vacuumworld/vwc/__init__.py
vacuumworld/vwc/action.py
vacuumworld-4.1.8.dist-info/LICENSE
vacuumworld-4.1.8.dist-info/METADATA
vacuumworld-4.1.8.dist-info/WHEEL
vacuumworld-4.1.8.dist-info/top_level.txt
vacuumworld-4.1.8.dist-info/RECORD
