Metadata-Version: 2.1
Name: vacuumworld
Version: 4.1.8
Summary: UNKNOWN
Home-page: https://github.com/dicelab-rhul/vacuumworld
Author: Benedict Wilkins
Author-email: brjw@hotmail.co.uk
License: GNU3
Platform: UNKNOWN
Classifier: Programming Language :: Python :: 3
Classifier: Programming Language :: Python :: 3.7
Classifier: Programming Language :: Python :: 3.8
Classifier: Programming Language :: Python :: 3.9
Classifier: Programming Language :: Python :: 3 :: Only
Classifier: Development Status :: 5 - Production/Stable
Classifier: License :: OSI Approved :: GNU General Public License v3 (GPLv3)
Classifier: Operating System :: OS Independent
Requires-Dist: pystarworlds (>=0.0.3)
Requires-Dist: pillow
Requires-Dist: wheel
Requires-Dist: ipython
Requires-Dist: screeninfo
